[{"JoinedParts": [0, 1], "JointData": {"BreakPoint": 8500, "Hardness": 0.98, "Type": "Solid", "Data": {}}, "PositionData": [[484.0, 348.0], [485.0, 347.0]], "SoundData": [["suspension_2.wav", 0.5], ["metal_crash_3.wav", 0.5], ["metal_crash_4.wav", 0.5]]}, {"JoinedParts": [0, 1], "JointData": {"BreakPoint": 8500, "Hardness": 0.98, "Type": "Solid", "Data": {}}, "PositionData": [[484.0, 348.0], [485.0, 347.0]], "SoundData": [["suspension_2.wav", 0.5], ["metal_crash_3.wav", 0.5], ["metal_crash_4.wav", 0.5]]}, {"JoinedParts": [0, 1], "JointData": {"BreakPoint": 8500, "Hardness": 0.98, "Type": "Solid", "Data": {}}, "PositionData": [[484.0, 348.0], [485.0, 347.0]], "SoundData": [["suspension_2.wav", 0.5], ["metal_crash_3.wav", 0.5], ["metal_crash_4.wav", 0.5]]}, {"JoinedParts": [0, 1], "JointData": {"BreakPoint": 8500, "Hardness": 0.98, "Type": "Solid", "Data": {}}, "PositionData": [[484.0, 348.0], [485.0, 347.0]], "SoundData": [["suspension_2.wav", 0.5], ["metal_crash_3.wav", 0.5], ["metal_crash_4.wav", 0.5]]}, {"JoinedParts": [1, 2], "JointData": {"BreakPoint": 8500, "Hardness": 0.98, "Type": "Solid", "Data": {}}, "PositionData": [[548.0, 348.0], [557.0, 354.0]], "SoundData": [["suspension_2.wav", 0.5], ["metal_crash_3.wav", 0.5], ["metal_crash_4.wav", 0.5]]}, {"JoinedParts": [1, 2], "JointData": {"BreakPoint": 8500, "Hardness": 0.98, "Type": "Solid", "Data": {}}, "PositionData": [[548.0, 348.0], [557.0, 354.0]], "SoundData": [["suspension_2.wav", 0.5], ["metal_crash_3.wav", 0.5], ["metal_crash_4.wav", 0.5]]}, {"JoinedParts": [1, 2], "JointData": {"BreakPoint": 8500, "Hardness": 0.98, "Type": "Solid", "Data": {}}, "PositionData": [[548.0, 348.0], [557.0, 354.0]], "SoundData": [["suspension_2.wav", 0.5], ["metal_crash_3.wav", 0.5], ["metal_crash_4.wav", 0.5]]}, {"JoinedParts": [1, 2], "JointData": {"BreakPoint": 8500, "Hardness": 0.98, "Type": "Solid", "Data": {}}, "PositionData": [[548.0, 348.0], [557.0, 354.0]], "SoundData": [["suspension_2.wav", 0.5], ["metal_crash_3.wav", 0.5], ["metal_crash_4.wav", 0.5]]}, {"JoinedParts": [0, 3], "JointData": {"BreakPoint": 10000, "Type": "Spring", "Data": {"Distance": 74, "Damping": 18, "Stiffness": 1200}}, "PositionData": [[420.0, 348.0], [415.62741699796953, 348.37258300203047]], "SoundData": [["tyre_1.wav", 1], ["tyre_2.wav", 1], ["tyre_3.wav", 1]]}, {"JoinedParts": [0, 3], "JointData": {"BreakPoint": 10000, "Type": "Spring", "Data": {"Distance": 74, "Damping": 18, "Stiffness": 1200}}, "PositionData": [[420.0, 348.0], [415.62741699796953, 348.37258300203047]], "SoundData": [["tyre_1.wav", 1], ["tyre_2.wav", 1], ["tyre_3.wav", 1]]}, {"JoinedParts": [0, 3], "JointData": {"BreakPoint": 10000, "Type": "Spring", "Data": {"Distance": 74, "Damping": 18, "Stiffness": 1200}}, "PositionData": [[420.0, 348.0], [415.62741699796953, 348.37258300203047]], "SoundData": [["tyre_1.wav", 1], ["tyre_2.wav", 1], ["tyre_3.wav", 1]]}, {"JoinedParts": [0, 3], "JointData": {"BreakPoint": 10000, "Type": "Spring", "Data": {"Distance": 74, "Damping": 18, "Stiffness": 1200}}, "PositionData": [[420.0, 348.0], [415.62741699796953, 348.37258300203047]], "SoundData": [["tyre_1.wav", 1], ["tyre_2.wav", 1], ["tyre_3.wav", 1]]}, {"JoinedParts": [2, 4], "JointData": {"BreakPoint": 10000, "Type": "Spring", "Data": {"Distance": 74, "Damping": 18, "Stiffness": 1200}}, "PositionData": [[612.0, 348.0], [622.3725830020305, 343.37258300203047]], "SoundData": [["tyre_1.wav", 1], ["tyre_2.wav", 1], ["tyre_3.wav", 1]]}, {"JoinedParts": [2, 4], "JointData": {"BreakPoint": 10000, "Type": "Spring", "Data": {"Distance": 74, "Damping": 18, "Stiffness": 1200}}, "PositionData": [[612.0, 348.0], [622.3725830020305, 343.37258300203047]], "SoundData": [["tyre_1.wav", 1], ["tyre_2.wav", 1], ["tyre_3.wav", 1]]}, {"JoinedParts": [2, 4], "JointData": {"BreakPoint": 10000, "Type": "Spring", "Data": {"Distance": 74, "Damping": 18, "Stiffness": 1200}}, "PositionData": [[612.0, 348.0], [622.3725830020305, 343.37258300203047]], "SoundData": [["tyre_1.wav", 1], ["tyre_2.wav", 1], ["tyre_3.wav", 1]]}, {"JoinedParts": [2, 4], "JointData": {"BreakPoint": 10000, "Type": "Spring", "Data": {"Distance": 74, "Damping": 18, "Stiffness": 1200}}, "PositionData": [[612.0, 348.0], [622.3725830020305, 343.37258300203047]], "SoundData": [["tyre_1.wav", 1], ["tyre_2.wav", 1], ["tyre_3.wav", 1]]}]